rtl/pattern_detection.v
module pattern_detection
(
	input clk_i,
	input reset_i,
	input data_i,
	output reg match_o
);

parameter IDLE 	= 2'd0;
parameter S1	= 2'd1;
parameter S10	= 2'd2;
parameter S101	= 2'd3;

reg [1:0]next_state;
reg [1:0]curr_state;

always@(posedge clk_i or negedge reset_i)
begin
	if(!reset_i)
	curr_state <= 2'd0;
	else
	curr_state <= next_state;
end

always@ *
begin
match_o = 1'd0;
next_state = IDLE;
case (curr_state)
	IDLE: 
	begin
		if(data_i == 1'd1)
		next_state = S1;
	end
	S1: 
	begin
		if(data_i == 1'd1)
		next_state = S1;
		else
		next_state = S10;
	end
	S10: 
	begin
		if(data_i == 1'd1)
		match_o = 1'd1;
	end
endcase
end
endmodule

tb/tb_sample.v
module tb();
reg clk_i, reset_i, data_i;
wire match_o;
pattern_detection pd0(.*);
initial
begin
	$dumpfile("sample.vcd");
	$dumpvars;
	clk_i = 1'd0;
	forever #5 clk_i = ~clk_i;
end

initial
begin
#0 reset_i <= 1'd1;
#5 reset_i <= 1'd0;
data_i <= 1'd0;
#10 reset_i <= 1'd1;
#10;
#10 data_i <= 1'd0;
#10 data_i <= 1'd1;
#10 data_i <= 1'd0;
#10 data_i <= 1'd0;
#10 data_i <= 1'd1;
#10 data_i <= 1'd0;
#10 data_i <= 1'd1;
#10 data_i <= 1'd1;
#10 data_i <= 1'd0;
#10 data_i <= 1'd1;
#20;
$finish;
end
endmodule

tb/sample.vcd
$date
	Tue Jul 23 22:42:23 2024
$end
$version
	Icarus Verilog
$end
$timescale
	1s
$end
$scope module tb $end
$var wire 1 ! match_o $end
$var reg 1 " clk_i $end
$var reg 1 # data_i $end
$var reg 1 $ reset_i $end
$scope module pd0 $end
$var wire 1 " clk_i $end
$var wire 1 # data_i $end
$var wire 1 $ reset_i $end
$var reg 2 % curr_state [1:0] $end
$var reg 1 ! match_o $end
$var reg 2 & next_state [1:0] $end
$upscope $end
$upscope $end
$enddefinitions $end
#0
$dumpvars
bx &
bx %
1$
x#
0"
x!
$end
#5
b0 %
b0 &
0!
0#
0$
1"
#10
0"
#15
1$
1"
#20
0"
#25
1"
#30
0"
#35
1"
#40
0"
#45
b1 &
1#
1"
#50
0"
#55
b10 &
b1 %
0#
1"
#60
0"
#65
b0 &
b10 %
1"
#70
0"
#75
b1 &
b0 %
1#
1"
#80
0"
#85
b10 &
b1 %
0#
1"
#90
0"
#95
1!
b0 &
b10 %
1#
1"
#100
0"
#105
b1 &
0!
b0 %
1"
#110
0"
#115
b10 &
b1 %
0#
1"
#120
0"
#125
1!
b0 &
b10 %
1#
1"
#130
0"
#135
b1 &
0!
b0 %
1"
#140
0"
#145
b1 &
b1 %
1"
